CHANGES.txt
MANIFEST.in
README.txt
development.ini
production.ini
setup.cfg
setup.py
scripts/prod_deamon_start.sh
sierra/__init__.py
sierra/tests.py
sierra/views.py
sierra.spicevan.com.egg-info/PKG-INFO
sierra.spicevan.com.egg-info/SOURCES.txt
sierra.spicevan.com.egg-info/dependency_links.txt
sierra.spicevan.com.egg-info/entry_points.txt
sierra.spicevan.com.egg-info/not-zip-safe
sierra.spicevan.com.egg-info/requires.txt
sierra.spicevan.com.egg-info/top_level.txt
sierra/static/favicon.ico
sierra/static/footerbg.png
sierra/static/headerbg.png
sierra/static/ie6.css
sierra/static/middlebg.png
sierra/static/pylons.css
sierra/static/pyramid-small.png
sierra/static/pyramid.png
sierra/static/transparent.gif
sierra/templates/abc.pt
sierra/templates/home.pt