Metadata-Version: 1.1
Name: sierra.spicevan.com
Version: 0.1.8
Summary: sierra.spicevan.com
Home-page: sierra.spicevan.com
Author: Fenton Travers
Author-email: fenton.travers@gmail.com
License: UNKNOWN
Keywords: web pyramid pylons
Platform: UNKNOWN
Classifier: Programming Language :: Python
Classifier: Framework :: Pyramid
Classifier: Topic :: Internet :: WWW/HTTP
Classifier: Topic :: Internet :: WWW/HTTP :: WSGI :: Application
